romus/__init__.py
romus/_blueprint.py
romus/_utils.py
romus/_version.py
romus/continuous_likelihood.py
romus/discrete_likelihood.py
romus/gibbs_samplers/__init__.py
romus/mixtures/__init__.py
tests/__init__.py
romus-0.0.1.dist-info/LICENSE.md
romus-0.0.1.dist-info/METADATA
romus-0.0.1.dist-info/WHEEL
romus-0.0.1.dist-info/top_level.txt
romus-0.0.1.dist-info/RECORD
