Metadata-Version: 2.1
Name: romus
Version: 0.0.1
Summary: Package for implementing bayesian deep conjugate models in python.
Home-page: UNKNOWN
Author: James Montgomery
Author-email: jamesoneillmontgomery@gmail.com
License: UNKNOWN
Platform: any
Classifier: Programming Language :: Python :: 3
Classifier: License :: OSI Approved :: MIT License
Classifier: Operating System :: OS Independent
Requires-Python: >=3.6
Requires-Dist: numpy (==1.18.1)
Requires-Dist: scipy (==1.4.1)
